Virtual_Assistant/__init__.py
Voice_Helper/__init__.py
voice_helper-0.2.dist-info/LICENSE
voice_helper-0.2.dist-info/METADATA
voice_helper-0.2.dist-info/WHEEL
voice_helper-0.2.dist-info/top_level.txt
voice_helper-0.2.dist-info/RECORD
