Metadata-Version: 2.1
Name: voice-helper
Version: 0.2
Summary: Custom virtual assistant
Home-page: UNKNOWN
Author: Eli Tremoulet
Author-email: <eliharvey007@hotmail.com>
License: UNKNOWN
Keywords: virtual assistant,voice assistant
Platform: UNKNOWN
Classifier: Development Status :: 1 - Planning
Classifier: Intended Audience :: Developers
Classifier: Programming Language :: Python :: 3
Classifier: Operating System :: Unix
Classifier: Operating System :: MacOS :: MacOS X
Classifier: Operating System :: Microsoft :: Windows
License-File: LICENSE
Requires-Dist: pyttsx3
Requires-Dist: SpeechRecognition
